camunda_client-0.12.0.dist-info/METADATA
camunda_client-0.12.0.dist-info/WHEEL
camunda_client-0.12.0.dist-info/entry_points.txt
camunda_client-0.12.0.dist-info/licenses/LICENSE
camunda_client/__init__.py
camunda_client/clients/__init__.py
camunda_client/clients/dto.py
camunda_client/clients/endpoints.py
camunda_client/clients/engine/__init__.py
camunda_client/clients/engine/client.py
camunda_client/clients/engine/dto.py
camunda_client/clients/engine/schemas/__init__.py
camunda_client/clients/engine/schemas/body.py
camunda_client/clients/engine/schemas/enums.py
camunda_client/clients/engine/schemas/query.py
camunda_client/clients/engine/schemas/response.py
camunda_client/clients/external_task/__init__.py
camunda_client/clients/external_task/client.py
camunda_client/clients/external_task/dto.py
camunda_client/clients/external_task/schemas/__init__.py
camunda_client/clients/external_task/schemas/body.py
camunda_client/clients/external_task/schemas/response.py
camunda_client/clients/schemas.py
camunda_client/clients/types_.py
camunda_client/exceptions.py
camunda_client/py.typed
camunda_client/types_.py
camunda_client/utils.py
camunda_client/worker/__init__.py
camunda_client/worker/context.py
camunda_client/worker/dto.py
camunda_client/worker/task_worker.py
camunda_client/worker/topic_consumer.py
camunda_client-0.12.0.dist-info/RECORD
