Metadata-Version: 2.1
Name: camunda-client
Version: 0.12.0
Summary: REST API Client for Camunda 7
Author-Email: Strana Dev <pypi@stranadev.ru>
License: Apache-2.0
Project-URL: Repository, https://github.com/stranadev/camunda-client
Requires-Python: >=3.11
Requires-Dist: pydantic>=2.8.2
Requires-Dist: httpx>=0.27.0
Requires-Dist: orjson>=3.10.7
